mediamagic/__init__.py
mediamagic/cli.py
mediamagic/downloader.py
mediamagic/main.py
mediamagic/media.py
mediamagic/setup.py
mediamagic/utils.py
mediamagic/platform/__init__.py
mediamagic/platform/spotify.py
mediamagic/platform/tiktok.py
mediamagic/platform/youtube.py
mediamagic/tests/__init__.py
mediamagic/tests/test_downloader.py
mediamagic/tests/test_media.py
MediaMagic-0.2.1.dist-info/METADATA
MediaMagic-0.2.1.dist-info/WHEEL
MediaMagic-0.2.1.dist-info/entry_points.txt
MediaMagic-0.2.1.dist-info/top_level.txt
MediaMagic-0.2.1.dist-info/RECORD
